salem/__init__.py
salem/datasets.py
salem/descartes.py
salem/gis.py
salem/graphics.py
salem/sio.py
salem/utils.py
salem/version.py
salem/wrftools.py
salem/tests/__init__.py
salem/tests/test_datasets.py
salem/tests/test_gis.py
salem/tests/test_graphics.py
salem/tests/test_misc.py
salem-0.3.11.dist-info/LICENSE.rst
salem-0.3.11.dist-info/METADATA
salem-0.3.11.dist-info/WHEEL
salem-0.3.11.dist-info/top_level.txt
salem-0.3.11.dist-info/RECORD
