Metadata-Version: 2.1
Name: salem
Version: 0.3.11
Summary: Geoscientific data I/O and map projections
Home-page: https://salem.readthedocs.io
Author: Fabien Maussion
Author-email: fabien.maussion@uibk.ac.at
License: BSD 3-clause
Project-URL: Documentation, https://salem.readthedocs.io
Project-URL: Source, https://github.com/fmaussion/salem
Project-URL: Tracker, https://github.com/fmaussion/salem/issues
Classifier: Development Status :: 3 - Alpha
Classifier: Intended Audience :: Science/Research
Classifier: License :: OSI Approved :: BSD License
Classifier: Topic :: Scientific/Engineering :: Atmospheric Science
Classifier: Topic :: Scientific/Engineering :: GIS
Classifier: Programming Language :: Python :: 3
Classifier: Programming Language :: Python :: 3.8
Classifier: Programming Language :: Python :: 3.9
Classifier: Programming Language :: Python :: 3.10
Classifier: Programming Language :: Python :: 3.11
Requires-Python: >=3.6
License-File: LICENSE.rst
Requires-Dist: numpy
Requires-Dist: scipy
Requires-Dist: pyproj
Requires-Dist: joblib
Requires-Dist: netCDF4
Requires-Dist: pandas
Requires-Dist: xarray
